sDNA/__init__.py
sDNA/__main__.py
sDNA/arc_import_itn.py
sDNA/arc_matchsymbologyranges.py
sDNA/arc_utils.py
sDNA/boxcox.R
sDNA/boxtidwell.R
sDNA/commandline_integral_prepare.py
sDNA/license.rtf
sDNA/placeholder.txt
sDNA/regularizedregression.R
sDNA/runcalculation.py
sDNA/runsdnacommand.py
sDNA/sDNA.pyt
sDNA/sDNAUISpec.py
sDNA/sDNA_ArcGIS_extra_tools.tbx
sDNA/sdna_environment.py
sDNA/sdnaexception.py
sDNA/sdnapy.py
sDNA/sdnaregutilities.py
sDNA/bin/README.txt
sDNA/bin/__init__.py
sDNA/bin/_parentdir.py
sDNA/bin/sdnaintegral.py
sDNA/bin/sdnalearn.py
sDNA/bin/sdnapredict.py
sDNA/bin/sdnaprepare.py
sDNA/x64/geos_c.dll
sDNA/x64/placeholder.txt
sDNA/x64/sdna_vs2008.dll
sdna_plus-5.0.2.dist-info/METADATA
sdna_plus-5.0.2.dist-info/WHEEL
sdna_plus-5.0.2.dist-info/entry_points.txt
sdna_plus-5.0.2.dist-info/licenses/LICENSE.md
sdna_plus-5.0.2.dist-info/RECORD
