Metadata-Version: 2.3
Name: sDNA_plus
Version: 5.0.2
Summary: sDNA is a world leading tool for Spatial Design Network Analysis.  
Project-URL: Homepage, https://sdna.cardiff.ac.uk/sdna/
Project-URL: Source code, https://github.com/fiftysevendegreesofrad/sdna_plus/tree/Cross_platform
Project-URL: Bug Tracker, https://github.com/fiftysevendegreesofrad/sdna_plus/issues
Author-email: Crispin Cooper <sdna@cardiff.ac.uk>, James Parrott <james.parrott@proton.me>
License: ## License for all sDNA code unless otherwise stated: AGPL v3.0
License-File: LICENSE.md
Keywords: GIS,Spatial Networks,Urban planning
Classifier: License :: OSI Approved :: GNU Affero General Public License v3
Classifier: Operating System :: Microsoft :: Windows
Classifier: Operating System :: POSIX :: Linux
Classifier: Programming Language :: Python
Requires-Python: >=3
Requires-Dist: pyshp==2.1.0
Provides-Extra: learn
Requires-Dist: numpy; extra == 'learn'
Provides-Extra: predict
Requires-Dist: numpy; extra == 'predict'
Provides-Extra: r
Requires-Dist: rportable[i386]==3.2.3; (platform_system == 'Windows') and extra == 'r'
